gil_py/__init__.py
gil_py/yaml_parser.py
gil_flow-0.1.0.dist-info/METADATA
gil_flow-0.1.0.dist-info/WHEEL
gil_flow-0.1.0.dist-info/entry_points.txt
gil_flow-0.1.0.dist-info/top_level.txt
gil_flow-0.1.0.dist-info/RECORD
