Metadata-Version: 2.4
Name: gil-flow
Version: 0.1.0
Summary: Gil-Flow: A language-neutral, YAML-based workflow system core SDK
Author-email: iyulab <caveman@iyulab.com>
License: MIT
Project-URL: Homepage, https://github.com/iyulab/gil
Project-URL: Repository, https://github.com/iyulab/gil
Project-URL: Documentation, https://github.com/iyulab/gil#readme
Project-URL: Issues, https://github.com/iyulab/gil/issues
Keywords: workflow,yaml,ai,automation,node-based,pipeline,sdk
Classifier: Development Status :: 4 - Beta
Classifier: Intended Audience :: Developers
Classifier: Programming Language :: Python :: 3
Classifier: Programming Language :: Python :: 3.8
Classifier: Programming Language :: Python :: 3.9
Classifier: Programming Language :: Python :: 3.10
Classifier: Programming Language :: Python :: 3.11
Classifier: Programming Language :: Python :: 3.12
Classifier: Topic :: Software Development :: Libraries :: Python Modules
Classifier: Topic :: Scientific/Engineering :: Artificial Intelligence
Classifier: Topic :: System :: Distributed Computing
Requires-Python: >=3.8
Requires-Dist: pydantic>=2.0.0
Requires-Dist: python-dotenv>=1.0.0
Requires-Dist: aiohttp>=3.8.0
Requires-Dist: click>=8.0.0
Requires-Dist: pyyaml>=6.0.0
Provides-Extra: dev
Requires-Dist: pytest>=7.0.0; extra == "dev"
Requires-Dist: pytest-asyncio>=0.21.0; extra == "dev"
Requires-Dist: black>=23.0.0; extra == "dev"
Requires-Dist: ruff>=0.0.270; extra == "dev"
Requires-Dist: mypy>=1.0.0; extra == "dev"
